edge_addons_api/__init__.py
edge_addons_api/client.py
edge_addons_api/exceptions.py
edge_addons_api-0.4.1.dist-info/LICENCE
edge_addons_api-0.4.1.dist-info/METADATA
edge_addons_api-0.4.1.dist-info/WHEEL
edge_addons_api-0.4.1.dist-info/RECORD
