Metadata-Version: 2.3
Name: edge-addons-api
Version: 0.4.1
Summary: API client for uploading addons to the Edge store
License: MIT
Author: Malachi Soord
Author-email: inverse.chi@gmail.com
Requires-Python: >=3.10,<4.0
Classifier: License :: OSI Approved :: MIT License
Classifier: Programming Language :: Python :: 3
Classifier: Programming Language :: Python :: 3.10
Classifier: Programming Language :: Python :: 3.11
Classifier: Programming Language :: Python :: 3.12
Classifier: Programming Language :: Python :: 3.13
Requires-Dist: requests (>=2.28.1,<3.0.0)
